personal_capital_plus-0.3.data/data/share/personalcapital/README.rst
personalcapital/__init__.py
personalcapital/analyze.py
personalcapital/connection.py
personalcapital/constants.py
personalcapital/database.py
personalcapital/etl.py
personalcapital/exceptions.py
personalcapital/log.py
personalcapital/version.py
personalcapital/tools/__init__.py
personalcapital/tools/entry.py
personal_capital_plus-0.3.dist-info/LICENSE
personal_capital_plus-0.3.dist-info/METADATA
personal_capital_plus-0.3.dist-info/WHEEL
personal_capital_plus-0.3.dist-info/entry_points.txt
personal_capital_plus-0.3.dist-info/top_level.txt
personal_capital_plus-0.3.dist-info/RECORD
