Metadata-Version: 2.1
Name: personal-capital-plus
Version: 0.3
Summary: Skeleton python application
Home-page: https://github.com/aagnone3/personal-capital-plus
Author: Anthony Agnone
Author-email: anthonyagnone@gmail.com
License: UNKNOWN
Platform: UNKNOWN
Classifier: Development Status :: 3 - Alpha
Classifier: Programming Language :: Python :: 3
Classifier: Topic :: Scientific/Engineering
Requires-Dist: requests (>=2.20.0)
Requires-Dist: pymongo
Requires-Dist: pandas
Requires-Dist: numpy
